practiso_sdk/__init__.py
practiso_sdk/archive.py
practiso_sdk/build.py
practiso_sdk/google/__init__.py
practiso_sdk/google/ai.py
practiso_sdk-1.0.0.dist-info/METADATA
practiso_sdk-1.0.0.dist-info/WHEEL
practiso_sdk-1.0.0.dist-info/licenses/LICENSE
practiso_sdk-1.0.0.dist-info/RECORD
