Metadata-Version: 2.4
Name: practiso-sdk
Version: 1.0.0
Summary: Practiso Software Development Kit
License-Expression: Apache-2.0
License-File: LICENSE
Author: zhufucdev
Author-email: zhufuzhufu1@gmail.com
Requires-Python: >=3.10
Classifier: Programming Language :: Python :: 3
Classifier: Programming Language :: Python :: 3.10
Classifier: Programming Language :: Python :: 3.11
Classifier: Programming Language :: Python :: 3.12
Classifier: Programming Language :: Python :: 3.13
Classifier: Programming Language :: Python :: 3.14
Provides-Extra: googleai
Requires-Dist: google-generativeai (>=0.8.3,<0.9.0) ; extra == "googleai"
Requires-Dist: pillow (>=11.0.0,<12.0.0)
Requires-Dist: tqdm (>=4.67.1,<5.0.0)
